{

    "name": "testMicroservice",
    "tags": "public permissions",
    "hostname": "testMicroservice",
    "httpPublicPort": 8080,
    "httpPrivatePort": 8081,
    "netGrpcUrl": "0.0.0.0:8082",
    "methods": {
        "createUser": {
            "public": true,
            "requestSchema": {
                "$ref": "./req.user.schema#"
            },
            "responseSchema": {
                "$ref": "./res.user.schema#"
            }
        },
        "updateUser": {
            "public": true,
            "requestSchema": {
                "$ref": "./req.user.schema#"
            },
            "responseSchema": {
                "$ref": "./res.user.schema#"
            }
        },
        "deleteUser": {
            "public": true,
            "requestSchema": {
                "$ref": "./req.user.schema#"
            },
            "responseSchema": {
                "$ref": "./res.user.schema#"
            }
        },
        "readUser": {
            "public": true,
            "requestSchema": {
                "$ref": "./req.user.schema#"
            },
            "responseSchema": {
                "$ref": "./res.user.schema#"
            }
        }
    },
    "listen": {
        "test": {
            "route": "test",
            "filter": ["name"],
            "haveResponse": true
        }
    },
    "emit": {
        "viewUpdated": {
            "singleResponse": true,
            "waitResponse": true
        }
    }
}
